{
  "products": [
    {
      "id": 1,
      "name": "Computer",
      "price": 4300,
      "quantity": 600,
      "selected": false,
      "available": true
    },
    {
      "id": 2,
      "name": "Printer",
      "price": 4300,
      "quantity": 600,
      "selected": true,
      "available": true
    },
    {
      "id": 3,
      "name": "Tables",
      "price": 4300,
      "quantity": 600,
      "selected": false,
      "available": true
    },
    {
      "name": "Imprimantes",
      "price": "20",
      "quantity": "45",
      "selected": true,
      "available": true,
      "id": 5
    }
  ]
}